<?xml version="1.0" encoding="UTF-8"?>
<jboss-web>

    <resource-ref>
        <res-ref-name>jdbc/Staging</res-ref-name>
        <res-type>javax.sql.DataSource</res-type>
        <jndi-name>java:/env/jdbc/Staging</jndi-name>
    </resource-ref>

    <resource-env-ref>
        <resource-env-ref-name>kafkaAudit/bootstrapServers</resource-env-ref-name>
        <jndi-name>java:/env/kafkaAudit/bootstrapServers</jndi-name>
    </resource-env-ref>

    <resource-env-ref>
        <resource-env-ref-name>kafkaConsumer/bootstrapAddress</resource-env-ref-name>
        <jndi-name>java:/env/kafkaConsumer/bootstrapAddress</jndi-name>
    </resource-env-ref>

    <resource-env-ref>
        <resource-env-ref-name>kafkaAudit/SecurityProtocol</resource-env-ref-name>
        <jndi-name>java:/env/kafkaAudit/SecurityProtocol</jndi-name>
    </resource-env-ref>

    <resource-env-ref>
        <resource-env-ref-name>kafkaAudit/trustStoreLocation</resource-env-ref-name>
        <jndi-name>java:/env/kafkaAudit/trustStoreLocation</jndi-name>
    </resource-env-ref>

    <resource-env-ref>
        <resource-env-ref-name>kafkaAudit/trustStorePassword</resource-env-ref-name>
        <jndi-name>java:/env/kafkaAudit/trustStorePassword</jndi-name>
    </resource-env-ref>

    <resource-env-ref>
        <resource-env-ref-name>kafkaAudit/keyPassword</resource-env-ref-name>
        <jndi-name>java:/env/kafkaAudit/keyPassword</jndi-name>
    </resource-env-ref>

    <resource-env-ref>
        <resource-env-ref-name>kafkaAudit/keyStorePassword</resource-env-ref-name>
        <jndi-name>java:/env/kafkaAudit/keyStorePassword</jndi-name>
    </resource-env-ref>

    <resource-env-ref>
        <resource-env-ref-name>kafkaAudit/keyStoreLocation</resource-env-ref-name>
        <jndi-name>java:/env/kafkaAudit/keyStoreLocation</jndi-name>
    </resource-env-ref>

    <resource-env-ref>
        <resource-env-ref-name>kafka/PersistService/appId</resource-env-ref-name>
        <jndi-name>java:/env/kafka/PersistService/appId</jndi-name>
    </resource-env-ref>

    <resource-env-ref>
        <resource-env-ref-name>kafkaAudit/topicName</resource-env-ref-name>
        <jndi-name>java:/env/kafka/topicName</jndi-name>
    </resource-env-ref>

    <resource-env-ref>
        <resource-env-ref-name>kafkaAudit/modeId</resource-env-ref-name>
        <jndi-name>java:/env/kafkaAudit/modeId</jndi-name>
    </resource-env-ref>

    <resource-env-ref>
        <resource-env-ref-name>PersistService/logs/filePath</resource-env-ref-name>
        <jndi-name>java:/env/PersistService/logs/filePath</jndi-name>
    </resource-env-ref>

    <resource-env-ref>
        <resource-env-ref-name>PersistService/logs/arhSize</resource-env-ref-name>
        <jndi-name>java:/env/PersistService/logs/arhSize</jndi-name>
    </resource-env-ref>

</jboss-web>